speech_recognition_api/__init__.py
speech_recognition_api/__main__.py
speech_recognition_api/bootstrap.py
speech_recognition_api/core/__init__.py
speech_recognition_api/core/config.py
speech_recognition_api/core/async_api/__init__.py
speech_recognition_api/core/async_api/async_api.py
speech_recognition_api/core/async_api/dependencies.py
speech_recognition_api/core/async_api/dto.py
speech_recognition_api/core/async_api/worker.py
speech_recognition_api/core/async_api/file_storage/__init__.py
speech_recognition_api/core/async_api/file_storage/builder.py
speech_recognition_api/core/async_api/file_storage/interface.py
speech_recognition_api/core/async_api/message_bus/__init__.py
speech_recognition_api/core/async_api/message_bus/builder.py
speech_recognition_api/core/async_api/message_bus/interface.py
speech_recognition_api/core/common/__init__.py
speech_recognition_api/core/common/buildable.py
speech_recognition_api/core/common/utils.py
speech_recognition_api/core/common/model/__init__.py
speech_recognition_api/core/common/model/builder.py
speech_recognition_api/core/common/model/interface.py
speech_recognition_api/core/sync_api/__init__.py
speech_recognition_api/core/sync_api/dependencies.py
speech_recognition_api/core/sync_api/dto.py
speech_recognition_api/core/sync_api/sync_api.py
speech_recognition_api/extra/__init__.py
speech_recognition_api/extra/audio_utils.py
speech_recognition_api/extra/celery_bus/__init__.py
speech_recognition_api/extra/celery_bus/celery_bus.py
speech_recognition_api/extra/celery_bus/config.py
speech_recognition_api/extra/google_cloud_storage/__init__.py
speech_recognition_api/extra/google_cloud_storage/config.py
speech_recognition_api/extra/google_cloud_storage/google_cloud_storage.py
speech_recognition_api/extra/huey_bus/__init__.py
speech_recognition_api/extra/huey_bus/config.py
speech_recognition_api/extra/huey_bus/huey_bus.py
speech_recognition_api/extra/local_storage/__init__.py
speech_recognition_api/extra/local_storage/config.py
speech_recognition_api-0.1.1.dist-info/LICENSE
speech_recognition_api-0.1.1.dist-info/METADATA
speech_recognition_api-0.1.1.dist-info/WHEEL
speech_recognition_api-0.1.1.dist-info/top_level.txt
speech_recognition_api-0.1.1.dist-info/RECORD
