Metadata-Version: 2.1
Name: speech-recognition-api
Version: 0.1.1
Summary: Simple but extensible API for Speech Recognition.
Author-email: Viktor Zhemchuzhnikov <asai5909@gmail.com>
Project-URL: Homepage, https://github.com/asai95/speech-recognition-api
Project-URL: Issues, https://github.com/asai95/speech-recognition-api/issues
Classifier: Programming Language :: Python :: 3 :: Only
Classifier: Programming Language :: Python :: 3.9
Classifier: Programming Language :: Python :: 3.10
Classifier: Programming Language :: Python :: 3.11
Classifier: License :: OSI Approved :: MIT License
Classifier: Operating System :: OS Independent
Requires-Python: <3.12,>=3.9
License-File: LICENSE
Requires-Dist: fastapi ~=0.105.0
Requires-Dist: pydantic ~=2.5.2
Requires-Dist: pydantic-settings ~=2.1.0
Requires-Dist: python-multipart ~=0.0.6
Requires-Dist: uvicorn ~=0.25.0
Provides-Extra: all
Requires-Dist: speech-recognition-api[celery,gcs,huey,s3,whisper] ; extra == 'all'
Provides-Extra: celery
Requires-Dist: celery ~=5.3.6 ; extra == 'celery'
Provides-Extra: gcs
Requires-Dist: google-cloud-storage ~=2.14.0 ; extra == 'gcs'
Provides-Extra: huey
Requires-Dist: huey ~=2.5.0 ; extra == 'huey'
Provides-Extra: s3
Requires-Dist: boto3 ~=1.34.5 ; extra == 's3'
Requires-Dist: boto3-type-annotations ~=0.3.1 ; extra == 's3'
Provides-Extra: whisper
Requires-Dist: transformers >=4.23.0 ; extra == 'whisper'
Requires-Dist: pydub ~=0.25.1 ; extra == 'whisper'
Requires-Dist: torch <=3.0.0,>=2.0.0 ; extra == 'whisper'
